ws_sbom_generator/__init__.py
ws_sbom_generator/_version.py
ws_sbom_generator/conftest.py
ws_sbom_generator/cyclonedx.py
ws_sbom_generator/sbom_generator.py
ws_sbom_generator-23.1.1.3.dist-info/LICENSE
ws_sbom_generator-23.1.1.3.dist-info/METADATA
ws_sbom_generator-23.1.1.3.dist-info/WHEEL
ws_sbom_generator-23.1.1.3.dist-info/entry_points.txt
ws_sbom_generator-23.1.1.3.dist-info/top_level.txt
ws_sbom_generator-23.1.1.3.dist-info/RECORD
