Metadata-Version: 2.1
Name: ws-sbom-generator
Version: 23.1.1.3
Summary: WS SBOM Generator in SPDX format
Home-page: https://github.com/whitesource-ps/ws-sbom-generator
Author: WhiteSource Professional Services
Author-email: ps@whitesourcesoftware.com
License: LICENSE.txt
Platform: UNKNOWN
Classifier: Programming Language :: Python :: 3.7
Classifier: Programming Language :: Python :: 3.8
Classifier: Programming Language :: Python :: 3.9
Classifier: License :: OSI Approved :: Apache Software License
Classifier: Operating System :: OS Independent
Requires-Python: >=3.7
License-File: LICENSE
Requires-Dist: ws-spdx-tools (==0.7.0a3.post7)
Requires-Dist: ws-sdk (==22.12.1.1)
Requires-Dist: numpy (==1.22.3)
